<?xml version="1.0" encoding="utf-8" ?>
<dwsync>
<file name="1.jpg" server="dev.maga.ro//var/www/maga/" local="130141499764601688" remote="130142176140000000" Dst="2" />
<file name="2.jpg" server="dev.maga.ro//var/www/maga/" local="130141499764606690" remote="130142176140000000" Dst="2" />
<file name="3.jpg" server="dev.maga.ro//var/www/maga/" local="130141499764621685" remote="130142176140000000" Dst="2" />
<file name="4.jpg" server="dev.maga.ro//var/www/maga/" local="130141499764661715" remote="130142176140000000" Dst="2" />
<file name="5.jpg" server="dev.maga.ro//var/www/maga/" local="130141499764816740" remote="130142176140000000" Dst="2" />
<file name="6.jpg" server="dev.maga.ro//var/www/maga/" local="130141499764821751" remote="130142176140000000" Dst="2" />
<file name="7.jpg" server="dev.maga.ro//var/www/maga/" local="130141499764831751" remote="130142176140000000" Dst="2" />
<file name="8.jpg" server="dev.maga.ro//var/www/maga/" local="130141499764851750" remote="130142176140000000" Dst="2" />
<file name="9.jpg" server="dev.maga.ro//var/www/maga/" local="130141499764931779" remote="130142176140000000" Dst="2" />
<file name="lista.php" server="dev.maga.ro//var/www/maga/" local="130141499764936780" remote="130142176140000000" Dst="2" />
</dwsync>